phazegod.py
phazegod-0.1.0.dist-info/licenses/LICENSE
phazegod-0.1.0.dist-info/METADATA
phazegod-0.1.0.dist-info/WHEEL
phazegod-0.1.0.dist-info/entry_points.txt
phazegod-0.1.0.dist-info/top_level.txt
phazegod-0.1.0.dist-info/RECORD
